[{
    "dt": "1711136700",
    "Partido": "Países Bajos - Escocia",
    "Competicion": "MLS",
    "Image": "",
    "Estadisticas": "https://apps-innova-redirects.blogspot.com/2020/03/no-disponible.html",
    "Switch": 0,
    "EnlaceMatchs": {
      "valor1": "",
      "valor2": "",
      "valor3": "",
      "valor4": "",
      "valor5": "",
      "valor6": ""
    }
  },
  {
    "dt": "1711139400",
    "Partido": "España - Colombia",
    "Competicion": "MLS",
    "Image": "",
    "Estadisticas": "https://apps-innova-redirects.blogspot.com/2020/03/no-disponible.html",
    "Switch": 0,
    "EnlaceMatchs": {
      "valor1": "",
      "valor2": "",
      "valor3": "",
      "valor4": "",
      "valor5": "",
      "valor6": ""
    }
  },
  {
    "dt": "1711152000",
    "Partido": "Argentina - El Salvador",
    "Competicion": "MLS",
    "Image": "",
    "Estadisticas": "https://apps-innova-redirects.blogspot.com/2020/03/no-disponible.html",
    "Switch": 0,
    "EnlaceMatchs": {
      "valor1": "",
      "valor2": "",
      "valor3": "",
      "valor4": "",
      "valor5": "",
      "valor6": ""
    }
  }
]
